{
  "document_id": "53624ca0e75b25c0850e189d01971f30",
  "chunk_id": "53624ca0e75b25c0850e189d01971f30_46",
  "chunk_type": "page",
  "text": "## Page 46\n\nNational Classification of Occupations – 2015 Concordance Table\n\nNCO 2015 NCO 2004\n\nDivision 1 Managers\n\nSub- 11 Chief Executives, Senior Officials and Legislators\n\nDivision\n\nGroup 111 Legislators and Senior Officials\n\nFamily 1111 Legislators\n\n1111.0100 Elected Official, Union Government 1111.10\n\n1111.0200 Elected Official, State Government 1112.10\n\n1111.0300 Elected Official, Local Bodies 1113.10\n\n1111.9900 Legislators, Other 1119.90\n\nFamily 1112 Senior Government Officials\n\n1112.0100 Administrative Official, Union Government 1121.10\n\n1112.0200 Diplomat 1121.20\n\n1112.0300 Executive Officials, Union Government 1121.30\n\n1112.0400 Administrative Official, State Government 1122.10\n\n1112.0500 Executive Official, State Government 1122.20\n\n1112.0600 Administrative and Executive Officials, Quasi 1123.10\n\nGovernment (Central)\n\n1112.0700 Administrative & Executive Officials, Quasi 1123.20\n\nGovernment (State)\n\n1112.0800 Administrative and Executive Officials, Local 1124.10\n\nBodies\n\n1112.9900 Senior Government Officials, Other 1129.90\n\nFamily 1113 Traditional Chiefs and Heads of Villages\n\nVOLUME I 34",
  "embedding": null,
  "source": {
    "file_type": "application/pdf",
    "source_path": "s3://e2e-rag-system/data/raw/NCO_Vol_I_2015.pdf",
    "page_number": 46,
    "start_time": null,
    "end_time": null,
    "line_range": null,
    "bbox": null
  },
  "graph": {
    "graph_node_id": "53624ca0e75b25c0850e189d01971f30_46",
    "parent_id": "53624ca0e75b25c0850e189d01971f30_page46",
    "previous_id": "53624ca0e75b25c0850e189d01971f30_45",
    "next_id": "53624ca0e75b25c0850e189d01971f30_47"
  },
  "metadata": {
    "timestamp": "2025-08-09T01:28:56.685336Z",
    "tags": [],
    "layout_tags": [
      "page"
    ],
    "entities": [],
    "used_ocr": false,
    "is_multilingual": false,
    "num_images": 0,
    "num_tables": 0,
    "parse_chunk_duration": 219,
    "custom": {}
  }
}