{
  "document_id": "53624ca0e75b25c0850e189d01971f30",
  "chunk_id": "53624ca0e75b25c0850e189d01971f30_83",
  "chunk_type": "page",
  "text": "## Page 83\n\nNational Classification of Occupations – 2015 Concordance Table\n\nNCO 2015 NCO 2004\n\n2511.0103 Engineer – Packaging\n\n2511.0104 Engineer – Product Lifecycle Management (PLM)\n\n2511.0105 Analyst\n\n2511.0106 Support Engineer\n\n2511.9900 System Analysts, Other 2131.90\n\nFamily 2512 Software Developers\n\n2512.0100 Computer Programmer/Software Engineer 2132.10\n\n2512.0201 Software Engineer 2132.20\n\n2512.0202 Test Engineer – Software\n\n2512.0203 Design Engineer(Product Engineer)\n\n2512.0204 Software Developer – Application Development\n\n2512.0205 Junior Software Developer\n\n2512.0206 Engineer Trainee – IT Services\n\n2512.0207 Engineer Trainee – Engineering Analysis\n\n2512.0300 Programmer Analyst 2132.30\n\n2512.0301 Software Developer – Product Development and\n\nDelivery\n\n2512.0401 FPGA Design Engineer\n\n2512.0501 Embedded Software Engineer\n\n2512.0601 Design Engineer – Engineering Analysis\n\n2512.0701 Application Maintenance Engineer\n\n2512.0800 Programmer, Engineering and Scientific/System 2132.40\n\nProgrammer\n\nVOLUME I 71",
  "embedding": null,
  "source": {
    "file_type": "application/pdf",
    "source_path": "s3://e2e-rag-system/data/raw/NCO_Vol_I_2015.pdf",
    "page_number": 83,
    "start_time": null,
    "end_time": null,
    "line_range": null,
    "bbox": null
  },
  "graph": {
    "graph_node_id": "53624ca0e75b25c0850e189d01971f30_83",
    "parent_id": "53624ca0e75b25c0850e189d01971f30_page83",
    "previous_id": "53624ca0e75b25c0850e189d01971f30_82",
    "next_id": "53624ca0e75b25c0850e189d01971f30_84"
  },
  "metadata": {
    "timestamp": "2025-08-09T01:29:12.253865Z",
    "tags": [],
    "layout_tags": [
      "page"
    ],
    "entities": [],
    "used_ocr": false,
    "is_multilingual": false,
    "num_images": 0,
    "num_tables": 0,
    "parse_chunk_duration": 144,
    "custom": {}
  }
}