{
  "document_id": "53624ca0e75b25c0850e189d01971f30",
  "chunk_id": "53624ca0e75b25c0850e189d01971f30_154",
  "chunk_type": "page",
  "text": "## Page 154\n\nNational Classification of Occupations – 2015 Concordance Table\n\nNCO 2015 NCO 2004\n\n6223.9900 Deep Sea Fishery Workers, Other 6153.90\n\nFamily 6224 Hunters and Trappers\n\n6224.0300 Trapper 6154.30\n\n6224.0400 Tracker 6154.40\n\n6224.0500 Fish Overseer 6159.10\n\n6224.0600 Fisheries Inspector 6159.20\n\n6224.0700 Fieldman, Fish 6159.25\n\n6224.0800 Yard Officer 6159.30\n\n6224.0900 Fish Hatcher 6159.35\n\n6224.1000 Fish Curer 6159.40\n\n6224.1100 Fish Meal Maker 6159.45\n\n6224.1200 Rock Pilot 6159.50\n\n6224.1300 Man Duck 6159.55\n\n6224.1400 Net Maker 6159.60\n\n6224.9900 Hunters and Trappers, Other 6159.90\n\nSub- 63 Subsistence Farmers, Fishers, Hunters and\n\nDivision Gatherers\n\nGroup 631 Subsistence Crop Farmers\n\nFamily 6310 Subsistence Crop Farmers\n\n6310.0100 Tree Trimmer and Pruner 6200.10\n\n6310.9900 Subsistence Crop Farmers, Others 6200.90\n\nGroup 632 Subsistence Livestock Farmers\n\nVOLUME I 142",
  "embedding": null,
  "source": {
    "file_type": "application/pdf",
    "source_path": "s3://e2e-rag-system/data/raw/NCO_Vol_I_2015.pdf",
    "page_number": 154,
    "start_time": null,
    "end_time": null,
    "line_range": null,
    "bbox": null
  },
  "graph": {
    "graph_node_id": "53624ca0e75b25c0850e189d01971f30_154",
    "parent_id": "53624ca0e75b25c0850e189d01971f30_page154",
    "previous_id": "53624ca0e75b25c0850e189d01971f30_153",
    "next_id": "53624ca0e75b25c0850e189d01971f30_155"
  },
  "metadata": {
    "timestamp": "2025-08-09T01:29:37.528102Z",
    "tags": [],
    "layout_tags": [
      "page"
    ],
    "entities": [],
    "used_ocr": false,
    "is_multilingual": false,
    "num_images": 0,
    "num_tables": 0,
    "parse_chunk_duration": 128,
    "custom": {}
  }
}