{
  "document_id": "53624ca0e75b25c0850e189d01971f30",
  "chunk_id": "53624ca0e75b25c0850e189d01971f30_39",
  "chunk_type": "page",
  "text": "## Page 39\n\nNational Classification of Occupations – 2015 Introduction\n\nfalls, which is Textiles, Fur and Leather Products\n\nMachine Operators\n\n8153 Family 8153 denotes the Family under which the occupation\n\nis listed, which is Sewing Machine Operators\n\n8153.01 Occupation .011 indicates the Occupation under the given Family,\n\nwhich is Sewing Machine Operator, General\n\n8153.0111 Occupation 1 (the last digit in .0111) denotes the QP NOS\n\nreference i.e. Sewing Machine Operator published by\n\nQP NOS Reference\n\nApparel, Made-ups & Home Furnishing\n\nSample Code\n\nThe NCO 2015 Coding Structure can accommodate 9999 Families. There can be a maximum of\n\n99 Occupations under each Family. There can be a maximum of 99 QP NOS references per\n\nOccupation.\n\nConsidering the dynamics of the labour market and addition of new QP NOS by the SSCs over a\n\nperiod of time, the NCO 2015 codes would be reviewed and updated periodically. This eight\n\ndigit coding structure provides ample scope for addition of Families or Occupations to the NCO, if\n\nrequired, in the future.\n\n4.2 Mapping the Job Roles to the Sectors/Industry\n\nOnce the job roles/occupations were mapped as per ISCO 2008, they were also classified as per\n\nthe sector/industry in which they fit. This mapping will help the Career Counsellors to guide a\n\njobseeker in gaining the correct job as per the relevant sector. Thus, all the job roles in the newly\n\ncreated NCO 2015 were mapped to the relevant sectors. The data generated was then shared\n\nwith experts from the industries for validation.\n\n4.2.1 Mapping the Job Roles to NIC\n\nVOLUME I 27",
  "embedding": null,
  "source": {
    "file_type": "application/pdf",
    "source_path": "s3://e2e-rag-system/data/raw/NCO_Vol_I_2015.pdf",
    "page_number": 39,
    "start_time": null,
    "end_time": null,
    "line_range": null,
    "bbox": null
  },
  "graph": {
    "graph_node_id": "53624ca0e75b25c0850e189d01971f30_39",
    "parent_id": "53624ca0e75b25c0850e189d01971f30_page39",
    "previous_id": "53624ca0e75b25c0850e189d01971f30_38",
    "next_id": "53624ca0e75b25c0850e189d01971f30_40"
  },
  "metadata": {
    "timestamp": "2025-08-09T01:28:54.566911Z",
    "tags": [],
    "layout_tags": [
      "page"
    ],
    "entities": [],
    "used_ocr": false,
    "is_multilingual": false,
    "num_images": 0,
    "num_tables": 0,
    "parse_chunk_duration": 73,
    "custom": {}
  }
}